{
	"metadata": {
		"name": "Sahih Muslim",
		"section": {
			"4": "The Book of Prayers "
		},
		"section_detail": {
			"4": {
				"hadithnumber_first": 837,
				"hadithnumber_last": 1160,
				"arabicnumber_first": 377,
				"arabicnumber_last": 519.02
			}
		}
	},
	"hadiths": [
		{
			"hadithnumber": 1114,
			"arabicnumber": "500.02",
			"text": "Rapporté par Aisha رضي الله عنها : Lors de l’expédition de Tabuk, on a demandé au Messager d’Allah ﷺ quelle barrière (sutra) devait utiliser la personne en prière : il a répondu : « Comme le dossier d’une selle. »",
			"grades": [],
			"reference": {
				"book": 4,
				"hadith": 276
			}
		}
	]
}