{"metadata":{"name":"Sahih Muslim","section":{"6":"The Book of Prayer - Travellers"},"section_detail":{"6":{"hadithnumber_first":1570,"hadithnumber_last":1950,"arabicnumber_first":685.01,"arabicnumber_last":843.02}}},"hadiths":[{"hadithnumber":1583,"arabicnumber":"691","text":"Rapporté par Yahya ibn Yazid al-Huna’i : J’ai demandé à Anas ibn Malik au sujet du raccourcissement de la prière. Il a répondu : « Quand le Messager d’Allah ﷺ avait parcouru une distance de trois miles ou trois farsakh (Shu‘ba, l’un des rapporteurs, avait un doute à ce sujet), il priait deux rak‘as. »","grades":[],"reference":{"book":6,"hadith":14}}]}