{"metadata":{"name":"Sahih Muslim","section":{"6":"The Book of Prayer - Travellers"},"section_detail":{"6":{"hadithnumber_first":1570,"hadithnumber_last":1950,"arabicnumber_first":685.01,"arabicnumber_last":843.02}}},"hadiths":[{"hadithnumber":1781,"arabicnumber":"760.01","text":"Rapporté par Abu Huraira رضي الله عنه : Le Messager d’Allah ﷺ a dit : « Celui qui jeûne pendant le Ramadan avec foi et en espérant la récompense d’Allah, tous ses péchés passés seront pardonnés. Et celui qui prie la nuit du destin (Lailat-ul-Qadr) avec foi et en espérant la récompense d’Allah, tous ses péchés passés seront pardonnés. »","grades":[],"reference":{"book":6,"hadith":209}}]}