{
	"metadata": {
		"name": "Sahih Muslim",
		"section": {
			"6": "The Book of Prayer - Travellers"
		},
		"section_detail": {
			"6": {
				"hadithnumber_first": 1570,
				"hadithnumber_last": 1950,
				"arabicnumber_first": 685.01,
				"arabicnumber_last": 843.02
			}
		}
	},
	"hadiths": [
		{
			"hadithnumber": 1818,
			"arabicnumber": "775",
			"text": "Rapporté par Husain b. ‘Ali, d’après son père ‘Ali b. Abu Talib : Le Messager d’Allah ﷺ est venu une nuit voir ‘Ali et Fatima (la fille du Prophète) et leur a dit : « Ne priez-vous pas la prière de la nuit (Tahajjud) ? » J’ai répondu : « Ô Messager d’Allah, nos âmes sont entre les mains d’Allah ; quand Il veut nous réveiller, Il nous réveille. » Le Messager d’Allah ﷺ est reparti après ma réponse, en frappant sa main sur sa cuisse, et je l’ai entendu dire : « L’homme aime discuter sur beaucoup de choses. »",
			"grades": [],
			"reference": {
				"book": 6,
				"hadith": 246
			}
		}
	]
}