{"metadata":{"name":"Sahih Muslim","section":{"1":"The Book of Faith"},"section_detail":{"1":{"hadithnumber_first":93,"hadithnumber_last":533,"arabicnumber_first":8.01,"arabicnumber_last":222.02}}},"hadiths":[{"hadithnumber":259,"arabicnumber":"87","text":"Rapporté par ‘Abdur-Rahman b. Abu Bakra, d’après son père : Nous étions en compagnie du Messager d’Allah ﷺ lorsqu’il a dit : « Voulez-vous que je vous informe sur les plus graves des grands péchés ? » Il l’a répété trois fois, puis il a dit : « Associer quelqu’un à Allah, désobéir à ses parents, et le faux témoignage ou la fausse parole. » Le Prophète était allongé, puis il s’est redressé et il a tellement répété cela que nous avons souhaité qu’il se taise","grades":[],"reference":{"book":1,"hadith":165}}]}