{"metadata":{"name":"Sahih Muslim","section":{"15":"The Book of Pilgrimage"},"section_detail":{"15":{"hadithnumber_first":2791,"hadithnumber_last":3397,"arabicnumber_first":1177.01,"arabicnumber_last":1399.09}}},"hadiths":[{"hadithnumber":3107,"arabicnumber":"1286.03","text":"Rapporté par ‘Urwa : Ce hadith a été rapporté avec la même chaîne de transmetteurs. Et dans la version rapportée par Humaid, il y a cet ajout : « Hisham a dit : Al-nass (vitesse de la monture) est plus rapide que al-‘anaq. »","grades":[],"reference":{"book":15,"hadith":312}}]}