{
	"metadata": {
		"name": "Sahih Muslim",
		"section": {
			"15": "The Book of Pilgrimage"
		},
		"section_detail": {
			"15": {
				"hadithnumber_first": 2791,
				"hadithnumber_last": 3397,
				"arabicnumber_first": 1177.01,
				"arabicnumber_last": 1399.09
			}
		}
	},
	"hadiths": [
		{
			"hadithnumber": 3280,
			"arabicnumber": "1345.01",
			"text": "Rapporté par Anas b. Malik رضي الله عنه : Moi et Abu Talha sommes revenus avec le Messager d’Allah ﷺ. Safiyyah, l’épouse du Prophète, était assise derrière lui sur son chameau. Quand nous sommes arrivés aux environs de Médine, il disait : « Nous sommes ceux qui reviennent, qui se repentent, qui adorent leur Seigneur, qui Le louent », et il répétait cela jusqu’à notre entrée à Médine",
			"grades": [],
			"reference": {
				"book": 15,
				"hadith": 484
			}
		}
	]
}