{"metadata":{"name":"Sahih Muslim","section":{"18":"The Book of Divorce "},"section_detail":{"18":{"hadithnumber_first":3652,"hadithnumber_last":3742,"arabicnumber_first":1471.01,"arabicnumber_last":1491}}},"hadiths":[{"hadithnumber":3675,"arabicnumber":"1472.03","text":"Rapporté par Abu al-Sahba’ : Abu al-Sahba’ a dit à Ibn ‘Abbas : « Explique-nous, d’après tes connaissances, si les trois divorces prononcés en une seule fois n’étaient pas considérés comme un seul à l’époque du Messager d’Allah ﷺ et d’Abou Bakr. » Il répondit : « C’était bien le cas, mais lorsque, sous le califat de Omar رضي الله عنه, les gens se sont mis à prononcer le divorce fréquemment, il leur a permis de le faire (et de considérer trois prononcements en une seule fois comme effectifs). »","grades":[],"reference":{"book":18,"hadith":24}}]}