{"metadata":{"name":"Sahih Muslim","section":{"26":"The Book of Vows"},"section_detail":{"26":{"hadithnumber_first":4235,"hadithnumber_last":4253,"arabicnumber_first":1638.01,"arabicnumber_last":1645}}},"hadiths":[{"hadithnumber":4237,"arabicnumber":"1639.01","text":"Rapporté par Abdullah b. Umar رضي الله عنه : Le Messager d’Allah ﷺ a choisi un jour pour nous interdire de faire des vœux et a dit : « Cela ne change rien au destin ; c’est seulement un moyen d’obtenir quelque chose de la part d’une personne avare. »","grades":[],"reference":{"book":26,"hadith":3}}]}