{
	"metadata": {
		"name": "Sahih Muslim",
		"section": {
			"33": "The Book on Government"
		},
		"section_detail": {
			"33": {
				"hadithnumber_first": 4701,
				"hadithnumber_last": 4967,
				"arabicnumber_first": 1818.01,
				"arabicnumber_last": 1928.02
			}
		}
	},
	"hadiths": [
		{
			"hadithnumber": 4719,
			"arabicnumber": "1825",
			"text": "Rapporté par Abu Dharr : J’ai dit au Prophète ﷺ : « Messager d’Allah, ne veux-tu pas me confier une fonction publique ? » Il a posé sa main sur mon épaule et a dit : « Abu Dharr, tu es faible, et l’autorité est un dépôt. Au Jour du Jugement, elle sera une cause d’humiliation et de regret, sauf pour celui qui en assume les devoirs et s’en acquitte correctement. »",
			"grades": [],
			"reference": {
				"book": 33,
				"hadith": 19
			}
		}
	]
}