{"metadata":{"name":"Sahih Muslim","section":{"42":"The Book of Dreams"},"section_detail":{"42":{"hadithnumber_first":5897,"hadithnumber_last":5937,"arabicnumber_first":2261.01,"arabicnumber_last":2275}}},"hadiths":[{"hadithnumber":5926,"arabicnumber":"2268.04","text":"Rapporté par Jabir رضي الله عنه : Un Bédouin est venu voir le Messager d’Allah ﷺ et a dit : « Ô Messager d’Allah, j’ai rêvé que ma tête avait été coupée et que je la suivais en boitant. » Le Messager d’Allah ﷺ lui répondit : « Ne raconte pas aux gens les jeux inutiles du diable avec toi dans ton sommeil. » (Le narrateur ajoute :) J’ai aussi entendu le Messager d’Allah ﷺ dire plus tard dans un sermon : « Aucun d’entre vous ne doit raconter les jeux du diable avec lui dans ses rêves. »","grades":[],"reference":{"book":42,"hadith":30}}]}