{"metadata":{"name":"Sahih Muslim","section":{"44":"The Book of the Merits of the Companions"},"section_detail":{"44":{"hadithnumber_first":6169,"hadithnumber_last":6499,"arabicnumber_first":2381,"arabicnumber_last":2547}}},"hadiths":[{"hadithnumber":6384,"arabicnumber":"2485.01","text":"Rapporté par Abu Huraira رضي الله عنه : Omar رضي الله عنه passa devant Hassan alors qu’il récitait des vers dans la mosquée. Omar le regarda d’un air significatif, et Hassan répondit : « Je récitais déjà des vers alors qu’un meilleur que toi (le Prophète ﷺ) était présent ici. » Puis il se tourna vers Abu Huraira et lui dit : « Je t’adjure par Allah, n’as-tu pas entendu le Messager d’Allah ﷺ dire : “Hassan, réponds en mon nom ; ô Allah, aide-le avec l’Esprit Saint.” » Abu Huraira répondit : « Par Allah, c’est vrai, le Prophète a bien dit cela. »","grades":[],"reference":{"book":44,"hadith":214}}]}