{"metadata":{"name":"Sahih Muslim","section":{"45":"The Book of Virtue, Enjoining Good Manners, and Joining of the Ties of Kinship"},"section_detail":{"45":{"hadithnumber_first":6500,"hadithnumber_last":6722,"arabicnumber_first":2548.01,"arabicnumber_last":2642.02}}},"hadiths":[{"hadithnumber":6507,"arabicnumber":"2549.04","text":"Rapporté par Yazid b. Abu Habib رضي الله عنه, d’après Na’im, l’affranchi de Umm Salama, rapportant de ‘Abdullah b. ‘Amr b. ‘As رضي الله عنه : « Un homme est venu voir l’Envoyé d’Allah ﷺ et a dit : “Je te donne mon allégeance pour l’émigration et le jihad, cherchant la récompense uniquement d’Allah.” Le Prophète ﷺ lui a demandé : “L’un de tes parents est-il encore en vie ?” Il a répondu : “Oui, bien sûr, les deux sont vivants.” Le Prophète ﷺ a demandé : “Veux-tu vraiment la récompense d’Allah ?” Il a dit : “Oui.” Le Messager d’Allah ﷺ a alors dit : “Retourne auprès de tes parents et traite-les avec bonté.” »","grades":[],"reference":{"book":45,"hadith":7}}]}