{"metadata":{"name":"Sahih Muslim","section":{"3":"The Book of Menstruation"},"section_detail":{"3":{"hadithnumber_first":679,"hadithnumber_last":836,"arabicnumber_first":293.01,"arabicnumber_last":376.04}}},"hadiths":[{"hadithnumber":697,"arabicnumber":"303.03","text":"Rapporté par Ibn Abbas, d’après Ali رضي الله عنه : Nous avons envoyé al-Miqdad ibn al-Aswad au Messager d’Allah ﷺ pour lui demander ce qu’il fallait faire concernant le liquide prostatique qui sort de la partie intime. Le Messager d’Allah ﷺ a dit : « Fais les ablutions et lave ton sexe. »","grades":[],"reference":{"book":3,"hadith":19}}]}