{
	"metadata": {
		"name": "Sahih Muslim",
		"section": {
			"52": "Characteristics of the Day of Judgment, Paradise, and Hell"
		},
		"section_detail": {
			"52": {
				"hadithnumber_first": 7045,
				"hadithnumber_last": 7129,
				"arabicnumber_first": 2785,
				"arabicnumber_last": 2821.03
			}
		}
	},
	"hadiths": [
		{
			"hadithnumber": 7058,
			"arabicnumber": "2793",
			"text": "Rapporté par Abu Huraira : Le Messager d’Allah ﷺ a dit : « Si dix savants parmi les Juifs me suivaient, il ne resterait aucun Juif sur la surface de la terre qui n’embrasserait pas l’islam. »",
			"grades": [],
			"reference": {
				"book": 52,
				"hadith": 14
			}
		}
	]
}