{"metadata":{"name":"Sahih Muslim","section":{"52":"Characteristics of the Day of Judgment, Paradise, and Hell"},"section_detail":{"52":{"hadithnumber_first":7045,"hadithnumber_last":7129,"arabicnumber_first":2785,"arabicnumber_last":2821.03}}},"hadiths":[{"hadithnumber":7085,"arabicnumber":"2805.03","text":"Rapporté par Anas ibn Malik : Le Messager d’Allah ﷺ a dit : « Il sera dit aux non-croyants le Jour de la Résurrection : “Si tu possédais de l’or remplissant toute la terre, voudrais-tu t’en servir pour te libérer ?” Il répondra : “Oui.” Alors il lui sera dit : “On t’a demandé quelque chose de bien plus facile que cela (mais tu n’y as pas prêté attention).” »","grades":[],"reference":{"book":52,"hadith":39}}]}