{"metadata":{"name":"Sahih Muslim","section":{"55":"The Book of Zuhd and Softening of Hearts "},"section_detail":{"55":{"hadithnumber_first":7417,"hadithnumber_last":7522,"arabicnumber_first":2956,"arabicnumber_last":3014}}},"hadiths":[{"hadithnumber":7489,"arabicnumber":"2993","text":"Rapporté par Iyas b. Salama b. al-Akwa’ : Son père lui a rapporté qu’il avait entendu le Messager d’Allah ﷺ dire : « Une personne a éternué en ma présence et je lui ai dit : “Qu’Allah te fasse miséricorde.” Il a éternué une deuxième fois et le Messager d’Allah ﷺ a dit : “Il a un rhume (il n’est pas nécessaire de répondre).” »","grades":[],"reference":{"book":55,"hadith":72}}]}