{"metadata":{"name":"Sunan an Nasai","section":{"23":"The Book of Zakah"},"section_detail":{"23":{"hadithnumber_first":2435,"hadithnumber_last":2618,"arabicnumber_first":2435,"arabicnumber_last":2618}}},"hadiths":[{"hadithnumber":2583,"arabicnumber":2583,"text":"Rapporté par Zainab, l’épouse de ‘Abdullah : Le Messager d’Allah a dit aux femmes : “Faites la charité, même avec vos bijoux.” ‘Abdullah n’était pas un homme riche et elle lui a dit : “Puis-je donner ma charité à toi et aux enfants orphelins de mon frère ?” ‘Abdullah a répondu : “Demande au Messager d’Allah à ce sujet.” Elle raconte : Je suis donc allée voir le Messager d’Allah, et à sa porte j’ai trouvé une femme des Ansar qui s’appelait aussi Zainab, et elle posait la même question que moi. Bilal est sorti vers nous et nous lui avons dit : “Va demander au Messager d’Allah à ce sujet, mais ne lui dis pas qui nous sommes.” Il est allé voir le Messager d’Allah et il a dit : “Qui sont-elles ?” Il a répondu : “Zainab.” Il a demandé : “Laquelle ?” Il a dit : “Zainab Al-Ansariyyah.” Il a dit : “Oui, elles auront deux récompenses : la récompense pour le maintien des liens familiaux et la récompense pour la charité.”","grades":[{"name":"Abu Ghuddah","grade":"Sahih"},{"name":"Al-Albani","grade":"Sahih"},{"name":"Zubair Ali Zai","grade":"Sahih - Agreed Upon"}],"reference":{"book":23,"hadith":149}}]}