{
	"metadata": {
		"name": "Sunan an Nasai",
		"section": {
			"45": "The Book of Oaths (qasamah), Retaliation and Blood Money"
		},
		"section_detail": {
			"45": {
				"hadithnumber_first": 4706,
				"hadithnumber_last": 4869,
				"arabicnumber_first": 4706,
				"arabicnumber_last": 4869
			}
		}
	},
	"hadiths": [
		{
			"hadithnumber": 4731,
			"arabicnumber": 4731,
			"text": "Rapporté par 'Abdullah bin Buraidah : Un homme est venu voir le Prophète ﷺ et a dit : \"Cet homme a tué mon frère.\" Le Prophète ﷺ lui a dit : \"Va et tue-le comme il a tué ton frère.\" L’homme lui a alors dit : \"Crains Allah et pardonne-moi, car cela t’apportera une plus grande récompense et ce sera meilleur pour toi et pour ton frère le Jour de la Résurrection.\" Alors il l’a laissé partir. On a informé le Prophète ﷺ de cela, il a demandé à l’homme ce qu’il avait dit, et l’homme lui a raconté. Le Prophète ﷺ a dit : \"Le pardon serait meilleur pour toi que ce qu’il aurait fait pour toi le Jour de la Résurrection, lorsqu’il aurait dit : 'Ô Seigneur, demande-lui pourquoi il m’a tué",
			"grades": [
				{
					"name": "Abu Ghuddah",
					"grade": "Daif Isnaad"
				},
				{
					"name": "Al-Albani",
					"grade": "Daif Isnaad"
				},
				{
					"name": "Zubair Ali Zai",
					"grade": "Isnaad Hasan"
				}
			],
			"reference": {
				"book": 45,
				"hadith": 26
			}
		}
	]
}