{
	"metadata": {
		"name": "Sunan Ibn Majah",
		"section": {
			"6": "Chapters Regarding Funerals"
		},
		"section_detail": {
			"6": {
				"hadithnumber_first": 1433,
				"hadithnumber_last": 1637,
				"arabicnumber_first": 1433,
				"arabicnumber_last": 1637
			}
		}
	},
	"hadiths": [
		{
			"hadithnumber": 1529,
			"arabicnumber": 1529,
			"text": "Rapporté par ‘Abdullah bin ‘Amir bin Rabi’ah, d’après son père : Une femme noire est décédée et le Prophète (ﷺ) n’en a pas été informé. Lorsqu’il l’a appris, il a dit : “Pourquoi ne m’en avez-vous pas informé ?” Puis il a dit à ses Compagnons : “Mettez-vous en rangs pour prier sur elle,” et il a accompli la prière funéraire pour elle",
			"grades": [
				{
					"name": "Al-Albani",
					"grade": "Hasan Sahih"
				},
				{
					"name": "Muhammad Fouad Abd al-Baqi",
					"grade": "Hasan Sahih"
				},
				{
					"name": "Zubair Ali Zai",
					"grade": "Sahih"
				}
			],
			"reference": {
				"book": 6,
				"hadith": 97
			}
		}
	]
}