{
	"metadata": {
		"name": "Sunan Ibn Majah",
		"section": {
			"6": "Chapters Regarding Funerals"
		},
		"section_detail": {
			"6": {
				"hadithnumber_first": 1433,
				"hadithnumber_last": 1637,
				"arabicnumber_first": 1433,
				"arabicnumber_last": 1637
			}
		}
	},
	"hadiths": [
		{
			"hadithnumber": 1634,
			"arabicnumber": 1634,
			"text": "Rapporté par Umm Salamah bint Abi Umayyah, l’épouse du Prophète (ﷺ) : À l’époque du Messager d’Allah (ﷺ), quand une personne se levait pour prier, son regard ne dépassait pas ses pieds. Après la mort du Messager d’Allah (ﷺ), quand une personne priait, son regard ne dépassait pas l’endroit où elle posait son front en se prosternant. Puis Abou Bakr est mort et c’était ‘Umar (le calife). Alors, quand quelqu’un priait, son regard ne dépassait pas la Qiblah. Ensuite est venu le temps de ‘Uthman bin ‘Affan, il y a eu des troubles, et les gens ont commencé à regarder à droite et à gauche",
			"grades": [
				{
					"name": "Al-Albani",
					"grade": "Daif"
				},
				{
					"name": "Muhammad Fouad Abd al-Baqi",
					"grade": "Daif"
				},
				{
					"name": "Shuaib Al Arnaut",
					"grade": "Daif"
				},
				{
					"name": "Zubair Ali Zai",
					"grade": "Daif"
				}
			],
			"reference": {
				"book": 6,
				"hadith": 202
			}
		}
	]
}