{
	"metadata": {
		"name": "Sunan Ibn Majah",
		"section": {
			"12": "The Chapters on Business Transactions"
		},
		"section_detail": {
			"12": {
				"hadithnumber_first": 2137,
				"hadithnumber_last": 2307,
				"arabicnumber_first": 2137,
				"arabicnumber_last": 2307
			}
		}
	},
	"hadiths": [
		{
			"hadithnumber": 2258,
			"arabicnumber": 2258,
			"text": "Rapporté par Abu Jawza' : J'ai entendu Ibn 'Abbas permettre l'échange (de Dirhams contre Dirham, etc., avec un surplus), et cela a été rapporté de lui. Puis j'ai entendu qu'il avait changé d'avis. Je l'ai rencontré à La Mecque et je lui ai dit : \"J'ai entendu que tu avais changé d'avis.\" Il a dit : \"Oui. C'était juste mon opinion, mais Abu Sa'eed a rapporté du Messager d'Allah (ﷺ) qu'il a interdit l'échange (d'objets similaires avec un surplus)",
			"grades": [
				{
					"name": "Al-Albani",
					"grade": "Sahih"
				},
				{
					"name": "Muhammad Fouad Abd al-Baqi",
					"grade": "Sahih"
				},
				{
					"name": "Shuaib Al Arnaut",
					"grade": "Sahih"
				},
				{
					"name": "Zubair Ali Zai",
					"grade": "Isnaad Sahih"
				}
			],
			"reference": {
				"book": 12,
				"hadith": 122
			}
		}
	]
}