{
	"metadata": {
		"name": "Sunan Ibn Majah",
		"section": {
			"24": "The Chapters on Jihad"
		},
		"section_detail": {
			"24": {
				"hadithnumber_first": 2753,
				"hadithnumber_last": 2881,
				"arabicnumber_first": 2753,
				"arabicnumber_last": 2881
			}
		}
	},
	"hadiths": [
		{
			"hadithnumber": 2758,
			"arabicnumber": 2758,
			"text": "Rapporté par ‘Umar bin Khattab : J’ai entendu le Messager d’Allah (ﷺ) dire : « Celui qui équipe un combattant pour la cause d’Allah jusqu’à ce qu’il soit complètement équipé aura une récompense équivalente à la sienne, jusqu’à ce qu’il meure ou revienne. »",
			"grades": [
				{
					"name": "Al-Albani",
					"grade": "Daif"
				},
				{
					"name": "Muhammad Fouad Abd al-Baqi",
					"grade": "Daif"
				},
				{
					"name": "Shuaib Al Arnaut",
					"grade": "Sahih"
				},
				{
					"name": "Zubair Ali Zai",
					"grade": "Sahih"
				}
			],
			"reference": {
				"book": 24,
				"hadith": 6
			}
		}
	]
}