{
	"metadata": {
		"name": "Sunan Ibn Majah",
		"section": {
			"25": "Chapters on Hajj Rituals"
		},
		"section_detail": {
			"25": {
				"hadithnumber_first": 2882,
				"hadithnumber_last": 3119,
				"arabicnumber_first": 2882,
				"arabicnumber_last": 3119
			}
		}
	},
	"hadiths": [
		{
			"hadithnumber": 2883,
			"arabicnumber": 2883,
			"text": "Rapporté par Ibn ‘Abbas : Fadl a dit – ou inversement : “Le Messager d’Allah (ﷺ) a dit : ‘Celui qui a l’intention de faire le Hajj, qu’il se dépêche de le faire, car il pourrait tomber malade, perdre sa monture ou être confronté à un empêchement.’”",
			"grades": [
				{
					"name": "Al-Albani",
					"grade": "Hasan"
				},
				{
					"name": "Muhammad Fouad Abd al-Baqi",
					"grade": "Hasan"
				},
				{
					"name": "Zubair Ali Zai",
					"grade": "Hasan"
				}
			],
			"reference": {
				"book": 25,
				"hadith": 2
			}
		}
	]
}