{
	"metadata": {
		"name": "Sunan Ibn Majah",
		"section": {
			"25": "Chapters on Hajj Rituals"
		},
		"section_detail": {
			"25": {
				"hadithnumber_first": 2882,
				"hadithnumber_last": 3119,
				"arabicnumber_first": 2882,
				"arabicnumber_last": 3119
			}
		}
	},
	"hadiths": [
		{
			"hadithnumber": 2978,
			"arabicnumber": 2978,
			"text": "Rapporté par Mutarrif bin ‘Abdullah bin Shikhkhir : ‘Imran bin Husain m’a dit : « Je vais te raconter un hadith, afin qu’Allah t’en fasse profiter après ce jour. Sache que le Messager d’Allah (ﷺ) a fait accomplir la ‘Umrah à un groupe de sa famille pendant les dix (jours) de Dhul-Hijjah, et le Messager d’Allah (ﷺ) ne l’a pas interdit, aucune révélation n’est venue l’annuler, et peu importe ce que les autres peuvent dire. »",
			"grades": [
				{
					"name": "Al-Albani",
					"grade": "Sahih"
				},
				{
					"name": "Muhammad Fouad Abd al-Baqi",
					"grade": "Sahih"
				},
				{
					"name": "Shuaib Al Arnaut",
					"grade": "Sahih"
				},
				{
					"name": "Zubair Ali Zai",
					"grade": "Sahih Muslim"
				}
			],
			"reference": {
				"book": 25,
				"hadith": 97
			}
		}
	]
}