{
	"metadata": {
		"name": "Sunan Ibn Majah",
		"section": {
			"5": "Establishing the Prayer and the Sunnah Regarding Them"
		},
		"section_detail": {
			"5": {
				"hadithnumber_first": 803,
				"hadithnumber_last": 1432,
				"arabicnumber_first": 803,
				"arabicnumber_last": 1432
			}
		}
	},
	"hadiths": [
		{
			"hadithnumber": 876,
			"arabicnumber": 876,
			"text": "Rapporté par Anas bin Malik : Le Messager d’Allah (ﷺ) a dit : « Quand l’imam dit : “Sami’ Allahu liman hamidah (Allah entend ceux qui Le louent)”, dites : “Rabbana wa lakal-hamd (Ô notre Seigneur, à Toi la louange)”. »",
			"grades": [
				{
					"name": "Al-Albani",
					"grade": "Sahih"
				},
				{
					"name": "Muhammad Fouad Abd al-Baqi",
					"grade": "Sahih Lighairihi"
				},
				{
					"name": "Shuaib Al Arnaut",
					"grade": "Sahih"
				},
				{
					"name": "Zubair Ali Zai",
					"grade": "Sahih - Bukhari And Muslim"
				}
			],
			"reference": {
				"book": 5,
				"hadith": 74
			}
		}
	]
}