{"metadata":{"name":"Sunan Abu Dawud","section":{"11":"The Rites of Hajj (Kitab Al-Manasik Wa'l-Hajj)"},"section_detail":{"11":{"hadithnumber_first":1721,"hadithnumber_last":2045,"arabicnumber_first":1721,"arabicnumber_last":2045}}},"hadiths":[{"hadithnumber":1809,"arabicnumber":1809,"text":"Rapporté par ‘Abd Allah ibn Abbas : Al-Fadl ibn Abbas était assis derrière l’Envoyé d’Allah ﷺ sur le chameau. Une femme de la tribu de Khath‘am est venue demander au Prophète ﷺ une décision concernant le hajj. Al-Fadl la regardait et elle le regardait aussi. L’Envoyé d’Allah ﷺ détournait le visage de Fadl de l’autre côté. Elle dit : « Envoyé d’Allah ﷺ, le commandement d’Allah d’accomplir le hajj est venu alors que mon père est un vieil homme qui ne peut pas rester fermement assis sur un chameau. Puis-je accomplir le hajj à sa place ? » Il répondit : « Oui. » Cela se passa lors du Pèlerinage d’Adieu","grades":[{"name":"Al-Albani","grade":"Sahih"},{"name":"Muhammad Muhyi Al-Din Abdul Hamid","grade":"Sahih"},{"name":"Zubair Ali Zai","grade":"Sahih Bukhari (1513) Sahih Muslim (1334)"}],"reference":{"book":11,"hadith":89}}]}