{"metadata":{"name":"Sunan Abu Dawud","section":{"11":"The Rites of Hajj (Kitab Al-Manasik Wa'l-Hajj)"},"section_detail":{"11":{"hadithnumber_first":1721,"hadithnumber_last":2045,"arabicnumber_first":1721,"arabicnumber_last":2045}}},"hadiths":[{"hadithnumber":1921,"arabicnumber":1921,"text":"Rapporté par Ibrahim bin ‘Uqabah : Kuraib m’a dit qu’il avait demandé à Umamah bin Zaid : « Raconte-moi ce que tu as fait le soir où tu étais derrière le Messager d’Allah ﷺ. » Il répondit : « Nous sommes arrivés dans la vallée où les gens font agenouiller leurs chameaux pour se reposer la nuit. Le Messager d’Allah ﷺ a fait agenouiller sa chamelle, a uriné, puis a demandé de l’eau pour faire les ablutions, mais il les a faites légèrement. Je lui ai demandé : “La prière ?” Il répondit : “La prière est devant toi.” Il est alors remonté sur la chamelle jusqu’à ce que nous arrivions à Al-Muzdalifah. Là, l’iqamah pour la prière du coucher du soleil a été faite. Les gens ont fait agenouiller leurs chameaux à leur place. Les chameaux n’étaient pas encore déchargés que l’iqamah pour la prière du soir a été faite et il a prié. Ensuite, les gens ont déchargé les chameaux. » Le narrateur Muhammad ajoute dans sa version : « Qu’as-tu fait le matin ? » Il répondit : « Al-Fadl monta derrière lui et moi, je marchais à pied parmi les gens de Quraysh qui étaient devant. »","grades":[{"name":"Al-Albani","grade":"Sahih"},{"name":"Muhammad Muhyi Al-Din Abdul Hamid","grade":"Sahih"},{"name":"Shuaib Al Arnaut","grade":"Sahih"},{"name":"Zubair Ali Zai","grade":"Sahih Muslim (1280)"}],"reference":{"book":11,"hadith":201}}]}