{
	"metadata": {
		"name": "Sunan Abu Dawud",
		"section": {
			"20": "Tribute, Spoils, and Rulership (Kitab Al-Kharaj, Wal-Fai' Wal-Imarah)"
		},
		"section_detail": {
			"20": {
				"hadithnumber_first": 2928,
				"hadithnumber_last": 3088,
				"arabicnumber_first": 2928,
				"arabicnumber_last": 3088
			}
		}
	},
	"hadiths": [
		{
			"hadithnumber": 3002,
			"arabicnumber": 3002,
			"text": "Rapporté par Muhayyisah رضي الله عنه : Le Messager d’Allah ﷺ a dit : « Si vous remportez la victoire sur les hommes juifs, tuez-les. » Muhayyisah s’est alors jeté sur Shubaybah, un homme parmi les marchands juifs avec qui il avait des liens proches, et il l’a tué. À ce moment-là, Huwayyisah, le frère de Muhayyisah, n’était pas encore musulman et il était plus âgé que lui. Quand Muhayyisah a tué Shubaybah, Huwayyisah l’a frappé et a dit : « Ô ennemi d’Allah, par Allah, tu as bien profité de ses biens, vu la graisse que tu as dans le ventre grâce à lui. »",
			"grades": [
				{
					"name": "Al-Albani",
					"grade": "Daif"
				},
				{
					"name": "Muhammad Muhyi Al-Din Abdul Hamid",
					"grade": "Daif"
				},
				{
					"name": "Shuaib Al Arnaut",
					"grade": "Daif"
				},
				{
					"name": "Zubair Ali Zai",
					"grade": "Daif"
				}
			],
			"reference": {
				"book": 20,
				"hadith": 75
			}
		}
	]
}