{"metadata":{"name":"Sunan Abu Dawud","section":{"27":"Drinks (Kitab Al-Ashribah)"},"section_detail":{"27":{"hadithnumber_first":3669,"hadithnumber_last":3735,"arabicnumber_first":3669,"arabicnumber_last":3735}}},"hadiths":[{"hadithnumber":3711,"arabicnumber":3711,"text":"Rapporté par Aïsha رضي الله عنها : « On faisait tremper des dattes pour l’Envoyé d’Allah ﷺ dans une outre fermée par le haut et munie d’une ouverture. Ce qui était trempé le matin, il le buvait le soir, et ce qui était trempé le soir, il le buvait le matin. »","grades":[{"name":"Al-Albani","grade":"Sahih"},{"name":"Muhammad Muhyi Al-Din Abdul Hamid","grade":"Sahih"},{"name":"Zubair Ali Zai","grade":"Sahih Muslim (2005)"}],"reference":{"book":27,"hadith":43}}]}