{
	"metadata": {
		"name": "Sunan Abu Dawud",
		"section": {
			"41": "Types of Blood-Wit (Kitab Al-Diyat)"
		},
		"section_detail": {
			"41": {
				"hadithnumber_first": 4494,
				"hadithnumber_last": 4595,
				"arabicnumber_first": 4494,
				"arabicnumber_last": 4595
			}
		}
	},
	"hadiths": [
		{
			"hadithnumber": 4534,
			"arabicnumber": 4534,
			"text": "Rapporté par Aisha, la mère des croyants رضي الله عنها : Le Prophète ﷺ envoya Abu Jahm ibn Hudhayfah pour collecter la zakat. Un homme se disputa avec lui au sujet de sa sadaqa (zakat), et Abu Jahm le frappa et lui blessa la tête. Sa famille vint voir le Prophète ﷺ et dit : « Vengeance, Messager d’Allah ! » Le Prophète ﷺ dit : « Vous pouvez recevoir tant et tant. » Mais ils refusèrent. Il répéta : « Vous pouvez recevoir tant et tant. » Ils refusèrent encore. Il proposa une troisième fois, et ils acceptèrent. Le Prophète ﷺ dit : « Je vais informer les gens cet après-midi de votre accord. » Ils dirent : « Oui. » Le Messager d’Allah ﷺ s’adressa alors aux gens : « Ces croyants sont venus me demander réparation. Je leur ai proposé tant et tant, et ils ont accepté. Êtes-vous d’accord ? » Ils répondirent : « Non. » Les émigrés (muhajiroun) voulurent alors se venger, mais le Messager d’Allah ﷺ leur ordonna de s’arrêter, et ils obéirent. Il rappela ensuite la famille, augmenta la compensation et demanda : « Êtes-vous d’accord ? » Ils répondirent : « Oui. » Il dit : « Je vais informer les gens de votre accord. » Ils dirent : « Oui. » Le Prophète ﷺ s’adressa alors et demanda : « Êtes-vous d’accord ? » Ils répondirent : « Oui. »",
			"grades": [
				{
					"name": "Al-Albani",
					"grade": "Sahih"
				},
				{
					"name": "Muhammad Muhyi Al-Din Abdul Hamid",
					"grade": "Sahih"
				},
				{
					"name": "Zubair Ali Zai",
					"grade": "Daif"
				}
			],
			"reference": {
				"book": 41,
				"hadith": 41
			}
		}
	]
}