{
	"metadata": {
		"name": "Sahih al Bukhari",
		"section": {
			"23": "Funerals (Al-Janaa'iz)"
		},
		"section_detail": {
			"23": {
				"hadithnumber_first": 1237,
				"hadithnumber_last": 1394,
				"arabicnumber_first": 1237,
				"arabicnumber_last": 1394
			}
		}
	},
	"hadiths": [
		{
			"hadithnumber": 1356,
			"arabicnumber": 1356,
			"text": "Rapporté par Anas : Un jeune garçon juif servait le Prophète (ﷺ) et il tomba malade. Le Prophète (ﷺ) alla lui rendre visite. Il s’assit près de sa tête et l’invita à embrasser l’islam. Le garçon regarda son père, qui était assis là ; ce dernier lui dit d’obéir à Abul-Qasim, et le garçon embrassa l’islam. Le Prophète (ﷺ) sortit en disant : « Louange à Allah qui a sauvé ce garçon du Feu de l’Enfer. »",
			"grades": [],
			"reference": {
				"book": 23,
				"hadith": 109
			}
		}
	]
}