{
	"metadata": {
		"name": "Sahih al Bukhari",
		"section": {
			"25": "Hajj (Pilgrimage)"
		},
		"section_detail": {
			"25": {
				"hadithnumber_first": 1513,
				"hadithnumber_last": 1772,
				"arabicnumber_first": 1513,
				"arabicnumber_last": 1772
			}
		}
	},
	"hadiths": [
		{
			"hadithnumber": 1728,
			"arabicnumber": 1728,
			"text": "Rapporté par Abu Huraira : Le Messager d’Allah (ﷺ) a dit : « Ô Allah ! Pardonne à ceux qui se rasent la tête. » Les gens ont demandé : « Et aussi à ceux qui se coupent les cheveux courts ? » Le Prophète (ﷺ) a dit : « Ô Allah ! Pardonne à ceux qui se rasent la tête. » Les gens ont dit : « Et aussi à ceux qui se coupent les cheveux courts ? » Le Prophète (ﷺ) a invoqué Allah pour ceux qui se rasent la tête et, la troisième fois, il a dit : « Pardonne aussi à ceux qui se coupent les cheveux courts. »",
			"grades": [],
			"reference": {
				"book": 25,
				"hadith": 206
			}
		}
	]
}