{"metadata":{"name":"Sahih al Bukhari","section":{"30":"Fasting"},"section_detail":{"30":{"hadithnumber_first":1891,"hadithnumber_last":2007,"arabicnumber_first":1891,"arabicnumber_last":2007}}},"hadiths":[{"hadithnumber":1932,"arabicnumber":1932,"text":"Rapporté par Abu Bakr bin `Abdur-Rahman : Mon père et moi sommes allés chez `Aisha et elle a dit : « Je témoigne que le Messager d’Allah (ﷺ) se levait parfois le matin en état de Janaba après un rapport sexuel, pas à cause d’un rêve, puis il jeûnait ce jour-là. » Ensuite, il est allé voir Um Salama et elle a raconté la même chose","grades":[],"reference":{"book":30,"hadith":39}}]}