{
	"metadata": {
		"name": "Sahih al Bukhari",
		"section": {
			"34": "Sales and Trade"
		},
		"section_detail": {
			"34": {
				"hadithnumber_first": 2047,
				"hadithnumber_last": 2238,
				"arabicnumber_first": 2047,
				"arabicnumber_last": 2238
			}
		}
	},
	"hadiths": [
		{
			"hadithnumber": 2141,
			"arabicnumber": 2141,
			"text": "Rapporté par Jabir bin `Abdullah : Un homme avait décidé qu’un de ses esclaves serait affranchi après sa mort, puis il a eu besoin d’argent. Le Prophète (ﷺ) a alors pris l’esclave et a dit : « Qui veut acheter cet esclave de moi ? » Nu'aim bin `Abdullah l’a acheté pour un certain prix, et le Prophète (ﷺ) lui a remis l’esclave",
			"grades": [],
			"reference": {
				"book": 34,
				"hadith": 93
			}
		}
	]
}