{"metadata":{"name":"Sahih al Bukhari","section":{"41":"Agriculture"},"section_detail":{"41":{"hadithnumber_first":2320,"hadithnumber_last":2350,"arabicnumber_first":2320,"arabicnumber_last":2350}}},"hadiths":[{"hadithnumber":2349,"arabicnumber":2349,"text":"Rapporté par Sahl bin Sa`d : Nous étions très heureux le vendredi, car une vieille femme coupait des racines de silq, que nous plantions sur les bords de nos petits ruisseaux, et les cuisinait dans sa marmite avec quelques grains d'orge. (Ya'qub, le sous-narrateur, a dit : « Je pense que le narrateur a précisé que le plat ne contenait pas de graisse ni de graisse fondue (provenant de la viande). ») Après la prière du vendredi, nous allions chez elle et elle nous servait ce plat. C'est pourquoi nous étions heureux le vendredi. Nous ne prenions pas nos repas ni la sieste de midi avant la prière du vendredi (Jumua)","grades":[],"reference":{"book":41,"hadith":27}}]}