{
	"metadata": {
		"name": "Sahih al Bukhari",
		"section": {
			"54": "Conditions"
		},
		"section_detail": {
			"54": {
				"hadithnumber_first": 2712,
				"hadithnumber_last": 2737,
				"arabicnumber_first": 2712,
				"arabicnumber_last": 2737
			}
		}
	},
	"hadiths": [
		{
			"hadithnumber": 2736,
			"arabicnumber": 2736,
			"text": "Rapporté par Abu Huraira : Le Messager d’Allah (ﷺ) a dit : « Allah a quatre-vingt-dix-neuf noms, soit cent moins un, et celui qui les connaît entrera au Paradis. » (Voir aussi le hadith n°419, volume)",
			"grades": [],
			"reference": {
				"book": 54,
				"hadith": 23
			}
		}
	]
}