{
	"metadata": {
		"name": "Sahih al Bukhari",
		"section": {
			"60": "Prophets"
		},
		"section_detail": {
			"60": {
				"hadithnumber_first": 3326,
				"hadithnumber_last": 3488,
				"arabicnumber_first": 3326,
				"arabicnumber_last": 3488
			}
		}
	},
	"hadiths": [
		{
			"hadithnumber": 3460,
			"arabicnumber": 3460,
			"text": "Rapporté par Ibn `Abbas : J’ai entendu `Umar dire : « Qu’Allah maudisse untel ! Ne sait-il pas que le Prophète (ﷺ) a dit : Qu’Allah maudisse les Juifs car, bien qu’il leur était interdit (de manger) la graisse, ils l’ont fondue et l’ont vendue. »",
			"grades": [],
			"reference": {
				"book": 60,
				"hadith": 127
			}
		}
	]
}