{"metadata":{"name":"Sahih al Bukhari","section":{"61":"Virtues and Merits of the Prophet (pbuh) and his Companions"},"section_detail":{"61":{"hadithnumber_first":3489,"hadithnumber_last":3648,"arabicnumber_first":3489,"arabicnumber_last":3648}}},"hadiths":[{"hadithnumber":3592,"arabicnumber":3592,"text":"Rapporté par `Umar bin Taghlib : J'ai entendu le Messager d'Allah (ﷺ) dire : « À l’approche de l’Heure, vous combattrez des gens qui porteront des chaussures en poils ; et vous combattrez aussi des gens au visage plat comme des boucliers. »","grades":[],"reference":{"book":61,"hadith":99}}]}