{"metadata":{"name":"Sahih al Bukhari","section":{"63":"Merits of the Helpers in Madinah (Ansaar)"},"section_detail":{"63":{"hadithnumber_first":3776,"hadithnumber_last":3948,"arabicnumber_first":3776,"arabicnumber_last":3948}}},"hadiths":[{"hadithnumber":3822,"arabicnumber":3822,"text":"Rapporté par Jarir bin ‘Abdullah : Le Messager d’Allah (ﷺ) ne m’a jamais refusé l’entrée depuis que je suis devenu musulman, et chaque fois qu’il me voyait, il me souriait","grades":[],"reference":{"book":63,"hadith":47}}]}