{"metadata":{"name":"Sahih al Bukhari","section":{"64":"Military Expeditions led by the Prophet (pbuh) (Al-Maghaazi)"},"section_detail":{"64":{"hadithnumber_first":3949,"hadithnumber_last":4473,"arabicnumber_first":3949,"arabicnumber_last":4473}}},"hadiths":[{"hadithnumber":4237,"arabicnumber":4237,"text":"Rapporté par 'Anbasa bin Sa`id : Abu Huraira est venu voir le Prophète (ﷺ) et lui a demandé une part du butin de Khaybar. À ce moment-là, un des fils de Sa`id bin Al-`As a dit : « Ô Messager d’Allah (ﷺ) ! Ne lui donne rien. » Abu Huraira a alors dit au Prophète (ﷺ) : « C’est lui qui a tué Ibn Qauqal. » Le fils de Sa`id a répondu : « Comme c’est étrange ! Un cobaye venu de Qadum Ad-Dan… »","grades":[],"reference":{"book":64,"hadith":275}}]}