{
	"metadata": {
		"name": "Sahih al Bukhari",
		"section": {
			"66": "Virtues of the Qur'an"
		},
		"section_detail": {
			"66": {
				"hadithnumber_first": 4979,
				"hadithnumber_last": 5062,
				"arabicnumber_first": 4979,
				"arabicnumber_last": 5062
			}
		}
	},
	"hadiths": [
		{
			"hadithnumber": 4983,
			"arabicnumber": 4983,
			"text": "Rapporté par Jundub : Un jour, le Prophète (ﷺ) est tombé malade et n’a pas accompli la prière de la nuit (Tahajjud) pendant une ou deux nuits. Une femme (l’épouse d’Abu Lahab) est venue le voir et a dit : « Ô Muhammad ! Je ne vois que ton démon t’a quitté. » Alors Allah a révélé (Sourate Ad-Duha) : « Par le jour montant, et par la nuit quand elle s’assombrit (ou reste calme) : Ton Seigneur ne t’a ni abandonné, ni détesté. »",
			"grades": [],
			"reference": {
				"book": 66,
				"hadith": 5
			}
		}
	]
}