{"metadata":{"name":"Sahih al Bukhari","section":{"72":"Hunting, Slaughtering"},"section_detail":{"72":{"hadithnumber_first":5475,"hadithnumber_last":5544,"arabicnumber_first":5475,"arabicnumber_last":5544}}},"hadiths":[{"hadithnumber":5493,"arabicnumber":5493,"text":"Rapporté par Jabir : Nous sommes partis en expédition et l'armée s'appelait l'Armée du Khabt, avec Abu 'Ubaida comme commandant. Nous avons souffert d'une grande faim. Puis la mer a rejeté un énorme poisson mort appelé Al-`Anbar, comme on n'en avait jamais vu. Nous en avons mangé pendant une quinzaine de jours, puis Abu 'Ubaida a pris un de ses os (et en a fait une arche) sous laquelle un cavalier pouvait passer facilement","grades":[],"reference":{"book":72,"hadith":19}}]}