{
	"metadata": {
		"name": "Sahih al Bukhari",
		"section": {
			"75": "Patients"
		},
		"section_detail": {
			"75": {
				"hadithnumber_first": 5640,
				"hadithnumber_last": 5677,
				"arabicnumber_first": 5640,
				"arabicnumber_last": 5677
			}
		}
	},
	"hadiths": [
		{
			"hadithnumber": 5642,
			"arabicnumber": 5642,
			"text": "Rapporté par Abu Sa`id Al-Khudri et Abu Huraira : Le Prophète (ﷺ) a dit : « Aucune fatigue, maladie, tristesse, chagrin, douleur ou détresse n’atteint un musulman, même s’il ne s’agit que d’une piqûre d’épine, sans qu’Allah n’efface une partie de ses péchés à cause de cela. »",
			"grades": [],
			"reference": {
				"book": 75,
				"hadith": 2
			}
		}
	]
}