{
	"metadata": {
		"name": "Sahih al Bukhari",
		"section": {
			"75": "Patients"
		},
		"section_detail": {
			"75": {
				"hadithnumber_first": 5640,
				"hadithnumber_last": 5677,
				"arabicnumber_first": 5640,
				"arabicnumber_last": 5677
			}
		}
	},
	"hadiths": [
		{
			"hadithnumber": 5653,
			"arabicnumber": 5653,
			"text": "Rapporté par Anas bin Malik : J’ai entendu le Messager d’Allah (ﷺ) dire : « Allah a dit : ‘Si Je prive Mon serviteur de ses deux choses les plus chères (c’est-à-dire ses yeux) et qu’il reste patient, Je le ferai entrer au Paradis en compensation.’ »",
			"grades": [],
			"reference": {
				"book": 75,
				"hadith": 13
			}
		}
	]
}