{
	"metadata": {
		"name": "Sahih al Bukhari",
		"section": {
			"76": "Medicine"
		},
		"section_detail": {
			"76": {
				"hadithnumber_first": 5678,
				"hadithnumber_last": 5782,
				"arabicnumber_first": 5678,
				"arabicnumber_last": 5782
			}
		}
	},
	"hadiths": [
		{
			"hadithnumber": 5741,
			"arabicnumber": 5741,
			"text": "Rapporté par Al-Aswad : J’ai demandé à `Aisha s’il était permis de soigner une piqûre venimeuse (de serpent ou de scorpion) avec une ruqya. Elle a répondu : « Le Prophète (ﷺ) a autorisé le traitement des piqûres venimeuses par la ruqya. »",
			"grades": [],
			"reference": {
				"book": 76,
				"hadith": 56
			}
		}
	]
}