{
	"metadata": {
		"name": "Sahih al Bukhari",
		"section": {
			"78": "Good Manners and Form (Al-Adab)"
		},
		"section_detail": {
			"78": {
				"hadithnumber_first": 5970,
				"hadithnumber_last": 6226,
				"arabicnumber_first": 5970,
				"arabicnumber_last": 6226
			}
		}
	},
	"hadiths": [
		{
			"hadithnumber": 6013,
			"arabicnumber": 6013,
			"text": "Rapporté par Jarir bin `Abdullah : Le Prophète (ﷺ) a dit : « Celui qui n’est pas miséricordieux envers les autres ne recevra pas de miséricorde. »",
			"grades": [],
			"reference": {
				"book": 78,
				"hadith": 44
			}
		}
	]
}