{"metadata":{"name":"Sahih al Bukhari","section":{"83":"Oaths and Vows"},"section_detail":{"83":{"hadithnumber_first":6621,"hadithnumber_last":6707,"arabicnumber_first":6621,"arabicnumber_last":6707}}},"hadiths":[{"hadithnumber":6682,"arabicnumber":6682,"text":"Rapporté par Abu Huraira : Le Messager d'Allah (ﷺ) a dit : « (Voici) deux paroles très faciles à dire avec la langue, très lourdes dans la balance (des récompenses), et les plus aimées du Tout Miséricordieux (et ce sont) : Subhan Allahi wa bi-hamdihi ; Subhan Allahi-l-'Adhim. »","grades":[],"reference":{"book":83,"hadith":59}}]}