{"metadata":{"name":"Sahih al Bukhari","section":{"91":"Interpretation of Dreams"},"section_detail":{"91":{"hadithnumber_first":6982,"hadithnumber_last":7047,"arabicnumber_first":6982,"arabicnumber_last":7047}}},"hadiths":[{"hadithnumber":7008,"arabicnumber":7008,"text":"Rapporté par Abu Sa`id Al-Khudri : Le Messager d’Allah (ﷺ) a dit : « Pendant que je dormais, des gens m’ont été présentés (en rêve). Ils portaient des chemises, certaines couvraient seulement leur poitrine, d’autres étaient un peu plus longues. Puis `Umar bin Al-Khattab est passé devant moi, portant une chemise qu’il traînait derrière lui. » Les gens ont demandé : « Quelle interprétation donnes-tu à ce rêve, ô Messager d’Allah ? » Il a répondu : « La religion. »","grades":[],"reference":{"book":91,"hadith":26}}]}