{
	"metadata": {
		"name": "Sahih al Bukhari",
		"section": {
			"10": "Call to Prayers (Adhaan)"
		},
		"section_detail": {
			"10": {
				"hadithnumber_first": 603,
				"hadithnumber_last": 875,
				"arabicnumber_first": 603,
				"arabicnumber_last": 875
			}
		}
	},
	"hadiths": [
		{
			"hadithnumber": 719,
			"arabicnumber": 719,
			"text": "Rapporté par Anas bin Malik : Une fois, l'Iqama a été prononcée et le Messager d'Allah (ﷺ) s'est tourné vers nous et a dit : « Alignez vos rangs et tenez-vous plus proches les uns des autres, car je vous vois même derrière mon dos. »",
			"grades": [],
			"reference": {
				"book": 10,
				"hadith": 114
			}
		}
	]
}