{
	"metadata": {
		"name": "Sahih al Bukhari",
		"section": {
			"96": "Holding Fast to the Qur'an and Sunnah"
		},
		"section_detail": {
			"96": {
				"hadithnumber_first": 7268,
				"hadithnumber_last": 7370,
				"arabicnumber_first": 7268,
				"arabicnumber_last": 7370
			}
		}
	},
	"hadiths": [
		{
			"hadithnumber": 7346,
			"arabicnumber": 7346,
			"text": "Rapporté par Ibn `Umar : Il a entendu le Prophète, après avoir relevé la tête de l’inclinaison pendant la prière du matin, dire : « Ô Allah, notre Seigneur ! Toutes les louanges sont pour Toi. » Et dans la dernière rak‘a, il a dit : « Ô Allah ! Maudis untel et untel. » Puis Allah a révélé : « Ce n’est pas à toi (Ô Muhammad) de décider, (mais à Allah), qu’Il leur accorde Sa miséricorde ou qu’Il les punisse, car ce sont vraiment des injustes. »",
			"grades": [],
			"reference": {
				"book": 96,
				"hadith": 74
			}
		}
	]
}