{
	"metadata": {
		"name": "Sahih al Bukhari",
		"section": {
			"97": "Oneness, Uniqueness of Allah (Tawheed)"
		},
		"section_detail": {
			"97": {
				"hadithnumber_first": 7371,
				"hadithnumber_last": 7563,
				"arabicnumber_first": 7371,
				"arabicnumber_last": 7563
			}
		}
	},
	"hadiths": [
		{
			"hadithnumber": 7551,
			"arabicnumber": 7551,
			"text": "Rapporté par `Imran : J’ai dit : « Ô Messager d’Allah (ﷺ) ! Pourquoi quelqu’un devrait-il faire de bonnes actions ? » Le Prophète (ﷺ) a répondu : « Chacun trouvera facile de faire les actes qui le mèneront à la destination pour laquelle il a été créé. »",
			"grades": [],
			"reference": {
				"book": 97,
				"hadith": 176
			}
		}
	]
}