{"metadata":{"name":"Forty Hadith of an-Nawawi","section":{"1":"Forty Hadith of an-Nawawi"},"section_detail":{"1":{"hadithnumber_first":1,"hadithnumber_last":42,"arabicnumber_first":1,"arabicnumber_last":42}}},"hadiths":[{"hadithnumber":3,"arabicnumber":3,"text":"عن ابي عبد الرحمن عبد الله بن عمر بن الخطاب رضي الله عنهما قال: سمعت رسول الله صلى الله عليه و سلم يقول: بني الاسلام على خمس: شهادة ان لا اله الا الله وان محمدا رسول الله، واقام الصلاة، وايتاء الزكاة، وحج البيت، وصوم رمضان . [رواه البخاري] ، [ومسلم]","grades":[],"reference":{"book":1,"hadith":3}}]}